cloudflare_r2/__init__.py
cloudflare_r2/main.py
cloudflare_r2/nb.ipynb
cloudflare_r2-0.0.3.dist-info/LICENSE
cloudflare_r2-0.0.3.dist-info/METADATA
cloudflare_r2-0.0.3.dist-info/WHEEL
cloudflare_r2-0.0.3.dist-info/RECORD
